[{"name": "TorchDynamo Cache Lookup", "ph": "X", "ts": 22905, "dur": 29, "tid": 1, "pid": "CPU functions", "args": {}}, {"name": "Torch-Compiled Region", "ph": "X", "ts": 22944, "dur": 7608, "tid": 1, "pid": "CPU functions", "args": {}}, {"name": "aten::empty", "ph": "X", "ts": 30396, "dur": 29, "tid": 1, "pid": "CPU functions", "args": {}}, {"name": "triton_poi_fused_flip_0", "ph": "X", "ts": 30460, "dur": 54, "tid": 1, "pid": "CPU functions", "args": {}}, {"name": "TorchDynamo Cache Lookup", "ph": "X", "ts": 30625, "dur": 12, "tid": 1, "pid": "CPU functions", "args": {}}, {"name": "Torch-Compiled Region", "ph": "X", "ts": 30639, "dur": 135, "tid": 1, "pid": "CPU functions", "args": {}}, {"name": "aten::empty", "ph": "X", "ts": 30694, "dur": 8, "tid": 1, "pid": "CPU functions", "args": {}}, {"name": "triton_poi_fused_flip_0", "ph": "X", "ts": 30719, "dur": 31, "tid": 1, "pid": "CPU functions", "args": {}}, {"name": "TorchDynamo Cache Lookup", "ph": "X", "ts": 30818, "dur": 9, "tid": 1, "pid": "CPU functions", "args": {}}, {"name": "Torch-Compiled Region", "ph": "X", "ts": 30829, "dur": 116, "tid": 1, "pid": "CPU functions", "args": {}}, {"name": "aten::empty", "ph": "X", "ts": 30872, "dur": 8, "tid": 1, "pid": "CPU functions", "args": {}}, {"name": "triton_poi_fused_flip_0", "ph": "X", "ts": 30893, "dur": 29, "tid": 1, "pid": "CPU functions", "args": {}}, {"name": "TorchDynamo Cache Lookup", "ph": "X", "ts": 30987, "dur": 9, "tid": 1, "pid": "CPU functions", "args": {}}, {"name": "Torch-Compiled Region", "ph": "X", "ts": 30998, "dur": 121, "tid": 1, "pid": "CPU functions", "args": {}}, {"name": "aten::empty", "ph": "X", "ts": 31041, "dur": 8, "tid": 1, "pid": "CPU functions", "args": {}}, {"name": "triton_poi_fused_flip_0", "ph": "X", "ts": 31068, "dur": 29, "tid": 1, "pid": "CPU functions", "args": {}}, {"name": "TorchDynamo Cache Lookup", "ph": "X", "ts": 31163, "dur": 9, "tid": 1, "pid": "CPU functions", "args": {}}, {"name": "Torch-Compiled Region", "ph": "X", "ts": 31174, "dur": 101, "tid": 1, "pid": "CPU functions", "args": {}}, {"name": "aten::empty", "ph": "X", "ts": 31212, "dur": 6, "tid": 1, "pid": "CPU functions", "args": {}}, {"name": "triton_poi_fused_flip_0", "ph": "X", "ts": 31231, "dur": 25, "tid": 1, "pid": "CPU functions", "args": {}}, {"name": "TorchDynamo Cache Lookup", "ph": "X", "ts": 31313, "dur": 7, "tid": 1, "pid": "CPU functions", "args": {}}, {"name": "Torch-Compiled Region", "ph": "X", "ts": 31322, "dur": 99, "tid": 1, "pid": "CPU functions", "args": {}}, {"name": "aten::empty", "ph": "X", "ts": 31359, "dur": 6, "tid": 1, "pid": "CPU functions", "args": {}}, {"name": "triton_poi_fused_flip_0", "ph": "X", "ts": 31377, "dur": 25, "tid": 1, "pid": "CPU functions", "args": {}}, {"name": "TorchDynamo Cache Lookup", "ph": "X", "ts": 31458, "dur": 8, "tid": 1, "pid": "CPU functions", "args": {}}, {"name": "Torch-Compiled Region", "ph": "X", "ts": 31467, "dur": 98, "tid": 1, "pid": "CPU functions", "args": {}}, {"name": "aten::empty", "ph": "X", "ts": 31504, "dur": 7, "tid": 1, "pid": "CPU functions", "args": {}}, {"name": "triton_poi_fused_flip_0", "ph": "X", "ts": 31523, "dur": 24, "tid": 1, "pid": "CPU functions", "args": {}}, {"name": "TorchDynamo Cache Lookup", "ph": "X", "ts": 31602, "dur": 7, "tid": 1, "pid": "CPU functions", "args": {}}, {"name": "Torch-Compiled Region", "ph": "X", "ts": 31610, "dur": 97, "tid": 1, "pid": "CPU functions", "args": {}}, {"name": "aten::empty", "ph": "X", "ts": 31647, "dur": 6, "tid": 1, "pid": "CPU functions", "args": {}}, {"name": "triton_poi_fused_flip_0", "ph": "X", "ts": 31664, "dur": 24, "tid": 1, "pid": "CPU functions", "args": {}}, {"name": "TorchDynamo Cache Lookup", "ph": "X", "ts": 31743, "dur": 8, "tid": 1, "pid": "CPU functions", "args": {}}, {"name": "Torch-Compiled Region", "ph": "X", "ts": 31753, "dur": 97, "tid": 1, "pid": "CPU functions", "args": {}}, {"name": "aten::empty", "ph": "X", "ts": 31789, "dur": 7, "tid": 1, "pid": "CPU functions", "args": {}}, {"name": "triton_poi_fused_flip_0", "ph": "X", "ts": 31807, "dur": 24, "tid": 1, "pid": "CPU functions", "args": {}}, {"name": "TorchDynamo Cache Lookup", "ph": "X", "ts": 31886, "dur": 7, "tid": 1, "pid": "CPU functions", "args": {}}, {"name": "Torch-Compiled Region", "ph": "X", "ts": 31894, "dur": 97, "tid": 1, "pid": "CPU functions", "args": {}}, {"name": "aten::empty", "ph": "X", "ts": 31930, "dur": 7, "tid": 1, "pid": "CPU functions", "args": {}}, {"name": "triton_poi_fused_flip_0", "ph": "X", "ts": 31949, "dur": 24, "tid": 1, "pid": "CPU functions", "args": {}}, {"name": "TorchDynamo Cache Lookup", "ph": "X", "ts": 32027, "dur": 7, "tid": 1, "pid": "CPU functions", "args": {}}, {"name": "Torch-Compiled Region", "ph": "X", "ts": 32036, "dur": 96, "tid": 1, "pid": "CPU functions", "args": {}}, {"name": "aten::empty", "ph": "X", "ts": 32071, "dur": 7, "tid": 1, "pid": "CPU functions", "args": {}}, {"name": "triton_poi_fused_flip_0", "ph": "X", "ts": 32089, "dur": 25, "tid": 1, "pid": "CPU functions", "args": {}}, {"name": "TorchDynamo Cache Lookup", "ph": "X", "ts": 32168, "dur": 8, "tid": 1, "pid": "CPU functions", "args": {}}, {"name": "Torch-Compiled Region", "ph": "X", "ts": 32177, "dur": 96, "tid": 1, "pid": "CPU functions", "args": {}}, {"name": "aten::empty", "ph": "X", "ts": 32213, "dur": 6, "tid": 1, "pid": "CPU functions", "args": {}}, {"name": "triton_poi_fused_flip_0", "ph": "X", "ts": 32231, "dur": 24, "tid": 1, "pid": "CPU functions", "args": {}}, {"name": "TorchDynamo Cache Lookup", "ph": "X", "ts": 32309, "dur": 7, "tid": 1, "pid": "CPU functions", "args": {}}, {"name": "Torch-Compiled Region", "ph": "X", "ts": 32318, "dur": 96, "tid": 1, "pid": "CPU functions", "args": {}}, {"name": "aten::empty", "ph": "X", "ts": 32354, "dur": 6, "tid": 1, "pid": "CPU functions", "args": {}}, {"name": "triton_poi_fused_flip_0", "ph": "X", "ts": 32372, "dur": 24, "tid": 1, "pid": "CPU functions", "args": {}}, {"name": "TorchDynamo Cache Lookup", "ph": "X", "ts": 32451, "dur": 7, "tid": 1, "pid": "CPU functions", "args": {}}, {"name": "Torch-Compiled Region", "ph": "X", "ts": 32459, "dur": 96, "tid": 1, "pid": "CPU functions", "args": {}}, {"name": "aten::empty", "ph": "X", "ts": 32495, "dur": 7, "tid": 1, "pid": "CPU functions", "args": {}}, {"name": "triton_poi_fused_flip_0", "ph": "X", "ts": 32513, "dur": 24, "tid": 1, "pid": "CPU functions", "args": {}}, {"name": "TorchDynamo Cache Lookup", "ph": "X", "ts": 32591, "dur": 7, "tid": 1, "pid": "CPU functions", "args": {}}, {"name": "Torch-Compiled Region", "ph": "X", "ts": 32599, "dur": 95, "tid": 1, "pid": "CPU functions", "args": {}}, {"name": "aten::empty", "ph": "X", "ts": 32634, "dur": 7, "tid": 1, "pid": "CPU functions", "args": {}}, {"name": "triton_poi_fused_flip_0", "ph": "X", "ts": 32652, "dur": 24, "tid": 1, "pid": "CPU functions", "args": {}}, {"name": "TorchDynamo Cache Lookup", "ph": "X", "ts": 32730, "dur": 7, "tid": 1, "pid": "CPU functions", "args": {}}, {"name": "Torch-Compiled Region", "ph": "X", "ts": 32739, "dur": 96, "tid": 1, "pid": "CPU functions", "args": {}}, {"name": "aten::empty", "ph": "X", "ts": 32775, "dur": 7, "tid": 1, "pid": "CPU functions", "args": {}}, {"name": "triton_poi_fused_flip_0", "ph": "X", "ts": 32793, "dur": 24, "tid": 1, "pid": "CPU functions", "args": {}}, {"name": "TorchDynamo Cache Lookup", "ph": "X", "ts": 32871, "dur": 7, "tid": 1, "pid": "CPU functions", "args": {}}, {"name": "Torch-Compiled Region", "ph": "X", "ts": 32880, "dur": 95, "tid": 1, "pid": "CPU functions", "args": {}}, {"name": "aten::empty", "ph": "X", "ts": 32915, "dur": 7, "tid": 1, "pid": "CPU functions", "args": {}}, {"name": "triton_poi_fused_flip_0", "ph": "X", "ts": 32934, "dur": 23, "tid": 1, "pid": "CPU functions", "args": {}}, {"name": "TorchDynamo Cache Lookup", "ph": "X", "ts": 33011, "dur": 7, "tid": 1, "pid": "CPU functions", "args": {}}, {"name": "Torch-Compiled Region", "ph": "X", "ts": 33020, "dur": 96, "tid": 1, "pid": "CPU functions", "args": {}}, {"name": "aten::empty", "ph": "X", "ts": 33056, "dur": 7, "tid": 1, "pid": "CPU functions", "args": {}}, {"name": "triton_poi_fused_flip_0", "ph": "X", "ts": 33074, "dur": 24, "tid": 1, "pid": "CPU functions", "args": {}}, {"name": "TorchDynamo Cache Lookup", "ph": "X", "ts": 33152, "dur": 8, "tid": 1, "pid": "CPU functions", "args": {}}, {"name": "Torch-Compiled Region", "ph": "X", "ts": 33161, "dur": 97, "tid": 1, "pid": "CPU functions", "args": {}}, {"name": "aten::empty", "ph": "X", "ts": 33197, "dur": 7, "tid": 1, "pid": "CPU functions", "args": {}}, {"name": "triton_poi_fused_flip_0", "ph": "X", "ts": 33215, "dur": 24, "tid": 1, "pid": "CPU functions", "args": {}}, {"name": "TorchDynamo Cache Lookup", "ph": "X", "ts": 33294, "dur": 8, "tid": 1, "pid": "CPU functions", "args": {}}, {"name": "Torch-Compiled Region", "ph": "X", "ts": 33303, "dur": 96, "tid": 1, "pid": "CPU functions", "args": {}}, {"name": "aten::empty", "ph": "X", "ts": 33339, "dur": 7, "tid": 1, "pid": "CPU functions", "args": {}}, {"name": "triton_poi_fused_flip_0", "ph": "X", "ts": 33357, "dur": 24, "tid": 1, "pid": "CPU functions", "args": {}}]